Workbook

Sheet Guía
A1: Cómo usar este archivo
A3: Qué requiere aprobación | B3: Solo los mensajes que el negocio envía por iniciativa propia o cuando pasaron más de 24 h desde el último mensaje del cliente. Las respuestas del agente dentro de la conversación no la requieren (hoja "Mensajes del agente").
A4: Dónde se envían | B4: WhatsApp Manager → Plantillas de mensajes → Crear plantilla, en la cuenta de WhatsApp Business del número de producción de JNdelT.
A5: Orden sugerido | B5: 1) Fase 1: recordatorio de agendar, recordatorio y cambios de cita, retomar conversación. 2) Adicionales: dossier y reenganche, si se aprueban. 3) Futuro: bienvenida de formularios, solo si entran formularios o voz.
A6: Columnas a llenar | B6: Amarillas: Estado en Meta, Fecha de envío y Comentarios de Meta (hoja "Plantillas Meta"), y Aplicar (hoja "Mensajes del agente").
A7: Ejemplo de llenado | B7: Estado en Meta: Aprobada · Fecha de envío: 2026-10-20 · Comentarios de Meta: Reclasificada como MARKETING.
A8: Variables | B8: {{1}} es siempre el primer nombre validado (sin títulos ni nombres genéricos). Meta pide un ejemplo por variable; ya están en la columna "Variables y ejemplos".
A9: Fuentes | B9: Sugerencias de Javier (9 y 13 oct), prompt de Dapta para Lucía (estilo, nombre, objeciones, fechas y horas) y propuesta comercial §4.3: plantillas aprobadas para cualquier mensaje iniciado por el negocio.
A10: Pendiente técnico | B10: Ninguna de estas plantillas se envía todavía: falta construir los envíos programados (recordatorios, seguimiento) y el webhook de citas de GoHighLevel.
A11: Revisión 26 oct | B11: Se aplicaron los cambios en rojo de Javier (columna "Revisión de Javier" en la hoja "Plantillas Meta") y se agregaron 4 plantillas que pide su guion de Lucía (filas 11 a 14). Todas siguen en Borrador: ninguna se ha enviado a Meta.

Sheet Plantillas Meta
A1: Plantillas de WhatsApp para aprobación de Meta — JNdelT Real Estate
A2: Idioma: Español (es). Solo WhatsApp: Instagram no usa plantillas. Las columnas amarillas (Estado en Meta, Fecha de envío, Comentarios de Meta) son para llenar al enviarlas.
A4: # | B4: Nombre de la plantilla | C4: Categoría | D4: Prioridad | E4: Cuándo se envía | F4: Rol | G4: Encabezado | H4: Cuerpo (texto para Meta) | I4: Variables y ejemplos (Meta los pide) | J4: Pie de página | K4: Botones | L4: Estado en el sistema | M4: Notas de cumplimiento | N4: Estado en Meta | O4: Fecha de envío | P4: Comentarios de Meta | Q4: Revisión de Javier (26 oct)
A5: 1 | B5: jndelt_recordatorio_agendar | C5: UTILITY | D5: Fase 1 (§4.3) | E5: Calificó con prioridad alta, se le ofrecieron horarios y pasaron 24 h sin que eligiera. Reemplaza la plantilla interna pendiente_agenda. | F5: Lucía y Sonia | H5: Hola {{1}}, tu registro en JNdelT Real Estate está listo y solo falta reservar la conversación con un asesor. ¿Te muestro los horarios disponibles? | I5: {{1}} primer nombre = Andrea | K5: Respuesta rápida: "Ver horarios" · "Más adelante" | L5: Por construir: el flujo aún no envía mensajes fuera de la conversación. | M5: Al tocar "Ver horarios" se reabre la ventana de 24 h y el agente ofrece horarios reales del calendario (Dapta: no proponer horarios inventados). | N5: Borrador | Q5: Sin cambios.
A6: 2 | B6: jndelt_recordatorio_cita | C6: UTILITY | D6: Fase 1 (§4.3) | E6: 24 h antes de una cita confirmada. | F6: Lucía y Sonia | H6: Hola {{1}}, te recordamos tu cita con JNdelT Real Estate el {{2}} a las {{3}}, hora de Colombia, por {{4}}. ¿Nos confirmas que sigue en pie? Si necesitas cambiarla, avísanos por aquí. | I6: {{1}} = Andrea · {{2}} = martes 14 de octubre · {{3}} = 10:00 a. m. · {{4}} = llamada | K6: Respuesta rápida: "Confirmo" · "Necesito cambiarla" | L6: Por construir (recordatorio programado). | M6: Fecha en lenguaje natural y hora con a. m./p. m. (Dapta: fechas y horas naturales con periodo del día). | N6: Borrador | Q6: Javier: "déjame saber sobre este mensaje". Ajustado a "avísanos por aquí" (no mezcla "te recordamos" con "déjame") y se suma su pregunta del guion: "¿Nos confirmas que sigue en pie?".
A7: 3 | B7: jndelt_cita_confirmada | C7: UTILITY | D7: Fase 1 (§4.3) | E7: Cita reservada fuera de la conversación (enlace de GoHighLevel) o confirmada después de 24 h. | F7: Lucía y Sonia | H7: Hola {{1}}, tu cita con JNdelT Real Estate quedó confirmada para el {{2}} a las {{3}}, hora de Colombia, por {{4}}. Nuestro asesor te atenderá en ese momento. | I7: {{1}} = Andrea · {{2}} = martes 14 de octubre · {{3}} = 10:00 a. m. · {{4}} = videollamada | K7: — | L7: Por construir (webhook de citas de GoHighLevel). | M7: Solo se envía con la cita confirmada por GoHighLevel (no promete contacto sin cita). | N7: Borrador | Q7: Aceptado: "Nuestro asesor".
A8: 4 | B8: jndelt_cita_reprogramada | C8: UTILITY | D8: Fase 1 (§4.3) | E8: La cita se movió desde GoHighLevel. | F8: Lucía y Sonia | H8: Hola {{1}}, tu cita con JNdelT Real Estate cambió al {{2}} a las {{3}}, hora de Colombia. Si ese horario no te sirve, responde a este mensaje. | I8: {{1}} = Andrea · {{2}} = jueves 16 de octubre · {{3}} = 3:00 p. m. | K8: Respuesta rápida: "Me sirve" · "Necesito otro horario" | L8: Por construir (webhook de citas de GoHighLevel). | N8: Borrador | Q8: Sin cambios.
A9: 5 | B9: jndelt_cita_cancelada | C9: UTILITY | D9: Fase 1 (§4.3) | E9: La cita se canceló desde GoHighLevel. | F9: Lucía y Sonia | H9: Hola {{1}}, tu cita del {{2}} con JNdelT Real Estate fue cancelada. ¿Quieres que te muestre nuevos horarios? | I9: {{1}} = Andrea · {{2}} = martes 14 de octubre | K9: Respuesta rápida: "Ver horarios" · "Ahora no" | L9: Por construir (webhook de citas de GoHighLevel). | N9: Borrador | Q9: Sin cambios.
A10: 6 | B10: jndelt_retomar_conversacion | C10: MARKETING | D10: Fase 1 (§4.3) | E10: Conversación incompleta: la persona dejó de responder o pidió hablar en otro momento (Dapta: "¿Cuándo sería mejor momento?"). | F10: Lucía y Sonia | H10: Hola {{1}}, quedó pendiente terminar tu registro con nosotros en JNdelT Real Estate. ¿Seguimos donde quedamos? | I10: {{1}} = Andrea | J10: Responde SALIR para no recibir más mensajes | K10: Respuesta rápida: "Sí, sigamos" · "Ahora no" | L10: Por construir (seguimiento programado). | M10: Meta probablemente la clasifique como marketing; requiere manejar la baja (SALIR). | N10: Borrador | Q10: Javier: "con nosotros" en lugar de la marca. Se mantienen ambos ("con nosotros en JNdelT Real Estate"): una plantilla MARKETING sin el nombre del negocio tiene más riesgo de rechazo.
A11: 7 | B11: jndelt_dossier | C11: MARKETING | D11: Adicional A4 (§5) | E11: Envío del dossier a prioridad baja o no calificados cuando ya pasaron 24 h. | F11: Lucía y Sonia | G11: Documento (PDF del dossier) | H11: Hola {{1}}, te compartimos información de JNdelT Real Estate: cómo trabajamos, propiedades disponibles y por qué la exclusividad funciona. Cuando quieras avanzar, escríbenos por aquí. | I11: {{1}} = Andrea · Encabezado: dossier-jndelt.pdf | J11: Responde SALIR para no recibir más mensajes | K11: Respuesta rápida: "Quiero avanzar" · "No me interesa" | L11: Parcial: dentro de las 24 h ya se envía sin plantilla; falta el PDF y el envío posterior. | M11: Contenido del dossier según Javier: modelo de negocio, propiedades y tips de exclusividad. | N11: Borrador | Q11: Su propuesta de video (VSL) pasa a una plantilla aparte: jndelt_video_proceso (fila 15). El dossier en PDF queda como estaba.
A12: 8 | B12: jndelt_reenganche | C12: MARKETING | D12: Adicional A4 (§5) | E12: Nutrición: contacto de prioridad baja, a los 30-60 días. | F12: Lucía y Sonia | H12: Hola {{1}}, te escribimos de JNdelT Real Estate. Hace un tiempo nos contaste que estabas pensando en {{2}} una propiedad; ¿sigue en tus planes? | I12: {{1}} = Andrea · {{2}} = vender | J12: Responde SALIR para no recibir más mensajes | K12: Respuesta rápida: "Sí, quiero avanzar" · "Ahora no" | L12: Por construir (seguimiento programado). | M12: Fuera de la propuesta (§5: reenganche de archivados). Sin "interesado/a" para no asumir género. | N12: Borrador | Q12: Javier: "piensas". Ajustado a "estabas pensando en": "hace un tiempo nos contaste que piensas" mezcla tiempos verbales.
A13: 9 | B13: jndelt_bienvenida_formulario_propietario | C13: UTILITY | D13: Futuro (formularios o voz) | E13: Lead que llenó un formulario de Meta para vender o arrendar; primer mensaje del negocio. | F13: Lucía | H13: Hola {{1}}, mucho gusto, soy Lucía, la asistente virtual de JNdelT Real Estate. Gracias por escribirnos sobre tu propiedad. ¿Puedo hacerte unas preguntas breves para orientarte? | I13: {{1}} = Andrea | K13: Respuesta rápida: "Sí, continuemos" · "Más tarde" | L13: No aplica todavía: el alcance actual es entrante por WhatsApp e Instagram. | M13: Tomado del flujo de Dapta ("¿Tienes un minuto para responder dos preguntas breves?"). Se presenta como asistente virtual. | N13: Borrador | Q13: Tomada su versión, más cercana. Se mantiene pedir permiso antes de las preguntas (decisión del 26 oct) y "asistente virtual" (AC 09).
A14: 10 | B14: jndelt_bienvenida_formulario_comprador | C14: UTILITY | D14: Futuro (formularios o voz) | E14: Lead que llenó un formulario de Meta para comprar o arrendar. | F14: Sonia | H14: Hola {{1}}, soy Sonia, la asistente virtual de JNdelT Real Estate. Recibimos tu solicitud sobre las propiedades que buscas. ¿Tienes un minuto para unas preguntas breves? | I14: {{1}} = Andrea | K14: Respuesta rápida: "Sí, continuemos" · "Más tarde" | L14: No aplica todavía. | N14: Borrador | Q14: Su versión ("¿para vivir o como inversión?", con el inmueble de interés) queda en espera: Sonia está inactiva y necesita la variable del anuncio y un campo nuevo.
A15: 11 | B15: jndelt_video_proceso | C15: MARKETING | D15: Fase 1 (guion 26 oct) | E15: Después de presentar la propuesta, cuando pasaron más de 24 h (dentro de las 24 h se envía sin plantilla con propuesta_video). | F15: Lucía | G15: Video (proceso de venta) | H15: Hola {{1}}, para que tengas claro cómo trabajamos y qué puedes esperar al vender tu {{2}} con JNdelT Real Estate, te compartimos un video con nuestro proceso paso a paso. Cuando lo veas, cuéntanos qué te pareció. | I15: {{1}} = Andrea · {{2}} = apartamento · Encabezado: video del proceso | J15: Responde SALIR para no recibir más mensajes | K15: Respuesta rápida: "Agendar llamada" · "Tengo dudas" | L15: Por construir (seguimiento programado). Falta el video (parametros.comercial.propuesta.video_url). | M15: Propuesta de Javier (VSL). Sin minutos en el texto hasta tener el video. | N15: Borrador | Q15: Nueva: propuesta "Mi opción" de Javier en la fila del dossier.
A16: 12 | B16: jndelt_llamada_no_atendida | C16: UTILITY | D16: Fase 1 (guion 26 oct) | E16: La persona no contestó la llamada agendada. | F16: Lucía y Sonia | H16: Hola {{1}}, hoy no pudimos coincidir en la llamada con JNdelT Real Estate. ¿Quieres que la reprogramemos para otro día? | I16: {{1}} = Andrea | K16: Respuesta rápida: "Sí, reprogramar" · "Ahora no" | L16: Por construir (webhook de citas de GoHighLevel). | M16: El guion habla de visita; el encuentro es una llamada (decisión D1). | N16: Borrador | Q16: Nueva: "Si no llega a la visita" del guion de Javier.
A17: 13 | B17: jndelt_referencia_sin_aliado | C17: UTILITY | D17: Fase 1 (guion 26 oct) | E17: Pasó el plazo para conseguir un colega aliado (parametros.seguimiento.horas_para_aliado) sin encontrarlo. | F17: Lucía | H17: Hola {{1}}, te escribimos de JNdelT Real Estate: por ahora no logramos conectarte con un colega aliado para tu zona. Preferimos decírtelo con claridad para que puedas buscar otras opciones; gracias por tu confianza. | I17: {{1}} = Andrea | K17: — | L17: Por construir (seguimiento programado). Falta definir el plazo: 48 o 72 h. | M17: Texto del guion de Javier. | N17: Borrador | Q17: Nueva: nota sobre el plazo para el contacto referido.
A18: 14 | B18: jndelt_retomar_vencimiento_arriendo | C18: MARKETING | D18: Fase 1 (guion 26 oct) | E18: 30 días antes de que venza el contrato del inquilino (campo fin_contrato_arriendo). | F18: Lucía | H18: Hola {{1}}, te escribimos de JNdelT Real Estate. Nos contaste que el contrato de arriendo de tu {{2}} vence pronto; ¿quieres que retomemos el proceso de venta? | I18: {{1}} = Andrea · {{2}} = apartamento | J18: Responde SALIR para no recibir más mensajes | K18: Respuesta rápida: "Sí, retomemos" · "Ahora no" | L18: Por construir (seguimiento programado). | M18: Pedida en la nota del guion ("retomar contacto antes del vencimiento"). | N18: Borrador | Q18: Nueva: inmueble arrendado del guion de Javier.

Sheet Verificación
A1: Verificación contra las sugerencias de Javier, el prompt de Dapta y las reglas de Meta
A2: Las columnas con fórmula se recalculan si editas el cuerpo en "Plantillas Meta". Frases y emojis se calcularon al generar el archivo.
A4: Plantilla | B4: Caracteres (máx. 1024) | C4: Marca JNdelT | D4: Preguntas (máx. 1, Dapta) | E4: Frases (máx. 2-3, Dapta) | F4: Tuteo (sin "usted") | G4: Sin emojis (Javier/Dapta) | H4: No empieza con variable (Meta) | I4: No termina en variable (Meta) | J4: Usa primer nombre {{1}} | K4: No pide correo (Dapta) | L4: Resultado
A5: ='Plantillas Meta'!B5 | B5: =LEN('Plantillas Meta'!H5) | C5: =IF(ISNUMBER(SEARCH("JNdelT",'Plantillas Meta'!H5)),"Sí","No") | D5: =LEN('Plantillas Meta'!H5)-LEN(SUBSTITUTE('Plantillas Meta'!H5,"?","")) | E5: 2 | F5: =IF(ISNUMBER(SEARCH("usted",'Plantillas Meta'!H5)),"Revisar","Sí") | G5: Sí | H5: =IF(LEFT(TRIM('Plantillas Meta'!H5),2)="{{","No","Sí") | I5: =IF(RIGHT(TRIM('Plantillas Meta'!H5),2)="}}","No","Sí") | J5: =IF(ISNUMBER(SEARCH("{{1}}",'Plantillas Meta'!H5)),"Sí","No") | K5: =IF(ISNUMBER(SEARCH("correo",'Plantillas Meta'!H5)),"Revisar","Sí") | L5: =IF(AND(B5<=1024,C5="Sí",D5<=1,E5<=3,F5="Sí",G5="Sí",H5="Sí",I5="Sí",K5="Sí"),"Cumple","Revisar")
A6: ='Plantillas Meta'!B6 | B6: =LEN('Plantillas Meta'!H6) | C6: =IF(ISNUMBER(SEARCH("JNdelT",'Plantillas Meta'!H6)),"Sí","No") | D6: =LEN('Plantillas Meta'!H6)-LEN(SUBSTITUTE('Plantillas Meta'!H6,"?","")) | E6: 3 | F6: =IF(ISNUMBER(SEARCH("usted",'Plantillas Meta'!H6)),"Revisar","Sí") | G6: Sí | H6: =IF(LEFT(TRIM('Plantillas Meta'!H6),2)="{{","No","Sí") | I6: =IF(RIGHT(TRIM('Plantillas Meta'!H6),2)="}}","No","Sí") | J6: =IF(ISNUMBER(SEARCH("{{1}}",'Plantillas Meta'!H6)),"Sí","No") | K6: =IF(ISNUMBER(SEARCH("correo",'Plantillas Meta'!H6)),"Revisar","Sí") | L6: =IF(AND(B6<=1024,C6="Sí",D6<=1,E6<=3,F6="Sí",G6="Sí",H6="Sí",I6="Sí",K6="Sí"),"Cumple","Revisar")
A7: ='Plantillas Meta'!B7 | B7: =LEN('Plantillas Meta'!H7) | C7: =IF(ISNUMBER(SEARCH("JNdelT",'Plantillas Meta'!H7)),"Sí","No") | D7: =LEN('Plantillas Meta'!H7)-LEN(SUBSTITUTE('Plantillas Meta'!H7,"?","")) | E7: 2 | F7: =IF(ISNUMBER(SEARCH("usted",'Plantillas Meta'!H7)),"Revisar","Sí") | G7: Sí | H7: =IF(LEFT(TRIM('Plantillas Meta'!H7),2)="{{","No","Sí") | I7: =IF(RIGHT(TRIM('Plantillas Meta'!H7),2)="}}","No","Sí") | J7: =IF(ISNUMBER(SEARCH("{{1}}",'Plantillas Meta'!H7)),"Sí","No") | K7: =IF(ISNUMBER(SEARCH("correo",'Plantillas Meta'!H7)),"Revisar","Sí") | L7: =IF(AND(B7<=1024,C7="Sí",D7<=1,E7<=3,F7="Sí",G7="Sí",H7="Sí",I7="Sí",K7="Sí"),"Cumple","Revisar")
A8: ='Plantillas Meta'!B8 | B8: =LEN('Plantillas Meta'!H8) | C8: =IF(ISNUMBER(SEARCH("JNdelT",'Plantillas Meta'!H8)),"Sí","No") | D8: =LEN('Plantillas Meta'!H8)-LEN(SUBSTITUTE('Plantillas Meta'!H8,"?","")) | E8: 2 | F8: =IF(ISNUMBER(SEARCH("usted",'Plantillas Meta'!H8)),"Revisar","Sí") | G8: Sí | H8: =IF(LEFT(TRIM('Plantillas Meta'!H8),2)="{{","No","Sí") | I8: =IF(RIGHT(TRIM('Plantillas Meta'!H8),2)="}}","No","Sí") | J8: =IF(ISNUMBER(SEARCH("{{1}}",'Plantillas Meta'!H8)),"Sí","No") | K8: =IF(ISNUMBER(SEARCH("correo",'Plantillas Meta'!H8)),"Revisar","Sí") | L8: =IF(AND(B8<=1024,C8="Sí",D8<=1,E8<=3,F8="Sí",G8="Sí",H8="Sí",I8="Sí",K8="Sí"),"Cumple","Revisar")
A9: ='Plantillas Meta'!B9 | B9: =LEN('Plantillas Meta'!H9) | C9: =IF(ISNUMBER(SEARCH("JNdelT",'Plantillas Meta'!H9)),"Sí","No") | D9: =LEN('Plantillas Meta'!H9)-LEN(SUBSTITUTE('Plantillas Meta'!H9,"?","")) | E9: 2 | F9: =IF(ISNUMBER(SEARCH("usted",'Plantillas Meta'!H9)),"Revisar","Sí") | G9: Sí | H9: =IF(LEFT(TRIM('Plantillas Meta'!H9),2)="{{","No","Sí") | I9: =IF(RIGHT(TRIM('Plantillas Meta'!H9),2)="}}","No","Sí") | J9: =IF(ISNUMBER(SEARCH("{{1}}",'Plantillas Meta'!H9)),"Sí","No") | K9: =IF(ISNUMBER(SEARCH("correo",'Plantillas Meta'!H9)),"Revisar","Sí") | L9: =IF(AND(B9<=1024,C9="Sí",D9<=1,E9<=3,F9="Sí",G9="Sí",H9="Sí",I9="Sí",K9="Sí"),"Cumple","Revisar")
A10: ='Plantillas Meta'!B10 | B10: =LEN('Plantillas Meta'!H10) | C10: =IF(ISNUMBER(SEARCH("JNdelT",'Plantillas Meta'!H10)),"Sí","No") | D10: =LEN('Plantillas Meta'!H10)-LEN(SUBSTITUTE('Plantillas Meta'!H10,"?","")) | E10: 2 | F10: =IF(ISNUMBER(SEARCH("usted",'Plantillas Meta'!H10)),"Revisar","Sí") | G10: Sí | H10: =IF(LEFT(TRIM('Plantillas Meta'!H10),2)="{{","No","Sí") | I10: =IF(RIGHT(TRIM('Plantillas Meta'!H10),2)="}}","No","Sí") | J10: =IF(ISNUMBER(SEARCH("{{1}}",'Plantillas Meta'!H10)),"Sí","No") | K10: =IF(ISNUMBER(SEARCH("correo",'Plantillas Meta'!H10)),"Revisar","Sí") | L10: =IF(AND(B10<=1024,C10="Sí",D10<=1,E10<=3,F10="Sí",G10="Sí",H10="Sí",I10="Sí",K10="Sí"),"Cumple","Revisar")
A11: ='Plantillas Meta'!B11 | B11: =LEN('Plantillas Meta'!H11) | C11: =IF(ISNUMBER(SEARCH("JNdelT",'Plantillas Meta'!H11)),"Sí","No") | D11: =LEN('Plantillas Meta'!H11)-LEN(SUBSTITUTE('Plantillas Meta'!H11,"?","")) | E11: 2 | F11: =IF(ISNUMBER(SEARCH("usted",'Plantillas Meta'!H11)),"Revisar","Sí") | G11: Sí | H11: =IF(LEFT(TRIM('Plantillas Meta'!H11),2)="{{","No","Sí") | I11: =IF(RIGHT(TRIM('Plantillas Meta'!H11),2)="}}","No","Sí") | J11: =IF(ISNUMBER(SEARCH("{{1}}",'Plantillas Meta'!H11)),"Sí","No") | K11: =IF(ISNUMBER(SEARCH("correo",'Plantillas Meta'!H11)),"Revisar","Sí") | L11: =IF(AND(B11<=1024,C11="Sí",D11<=1,E11<=3,F11="Sí",G11="Sí",H11="Sí",I11="Sí",K11="Sí"),"Cumple","Revisar")
A12: ='Plantillas Meta'!B12 | B12: =LEN('Plantillas Meta'!H12) | C12: =IF(ISNUMBER(SEARCH("JNdelT",'Plantillas Meta'!H12)),"Sí","No") | D12: =LEN('Plantillas Meta'!H12)-LEN(SUBSTITUTE('Plantillas Meta'!H12,"?","")) | E12: 2 | F12: =IF(ISNUMBER(SEARCH("usted",'Plantillas Meta'!H12)),"Revisar","Sí") | G12: Sí | H12: =IF(LEFT(TRIM('Plantillas Meta'!H12),2)="{{","No","Sí") | I12: =IF(RIGHT(TRIM('Plantillas Meta'!H12),2)="}}","No","Sí") | J12: =IF(ISNUMBER(SEARCH("{{1}}",'Plantillas Meta'!H12)),"Sí","No") | K12: =IF(ISNUMBER(SEARCH("correo",'Plantillas Meta'!H12)),"Revisar","Sí") | L12: =IF(AND(B12<=1024,C12="Sí",D12<=1,E12<=3,F12="Sí",G12="Sí",H12="Sí",I12="Sí",K12="Sí"),"Cumple","Revisar")
A13: ='Plantillas Meta'!B13 | B13: =LEN('Plantillas Meta'!H13) | C13: =IF(ISNUMBER(SEARCH("JNdelT",'Plantillas Meta'!H13)),"Sí","No") | D13: =LEN('Plantillas Meta'!H13)-LEN(SUBSTITUTE('Plantillas Meta'!H13,"?","")) | E13: 3 | F13: =IF(ISNUMBER(SEARCH("usted",'Plantillas Meta'!H13)),"Revisar","Sí") | G13: Sí | H13: =IF(LEFT(TRIM('Plantillas Meta'!H13),2)="{{","No","Sí") | I13: =IF(RIGHT(TRIM('Plantillas Meta'!H13),2)="}}","No","Sí") | J13: =IF(ISNUMBER(SEARCH("{{1}}",'Plantillas Meta'!H13)),"Sí","No") | K13: =IF(ISNUMBER(SEARCH("correo",'Plantillas Meta'!H13)),"Revisar","Sí") | L13: =IF(AND(B13<=1024,C13="Sí",D13<=1,E13<=3,F13="Sí",G13="Sí",H13="Sí",I13="Sí",K13="Sí"),"Cumple","Revisar")
A14: ='Plantillas Meta'!B14 | B14: =LEN('Plantillas Meta'!H14) | C14: =IF(ISNUMBER(SEARCH("JNdelT",'Plantillas Meta'!H14)),"Sí","No") | D14: =LEN('Plantillas Meta'!H14)-LEN(SUBSTITUTE('Plantillas Meta'!H14,"?","")) | E14: 3 | F14: =IF(ISNUMBER(SEARCH("usted",'Plantillas Meta'!H14)),"Revisar","Sí") | G14: Sí | H14: =IF(LEFT(TRIM('Plantillas Meta'!H14),2)="{{","No","Sí") | I14: =IF(RIGHT(TRIM('Plantillas Meta'!H14),2)="}}","No","Sí") | J14: =IF(ISNUMBER(SEARCH("{{1}}",'Plantillas Meta'!H14)),"Sí","No") | K14: =IF(ISNUMBER(SEARCH("correo",'Plantillas Meta'!H14)),"Revisar","Sí") | L14: =IF(AND(B14<=1024,C14="Sí",D14<=1,E14<=3,F14="Sí",G14="Sí",H14="Sí",I14="Sí",K14="Sí"),"Cumple","Revisar")
A15: ='Plantillas Meta'!B15 | B15: =LEN('Plantillas Meta'!H15) | C15: =IF(ISNUMBER(SEARCH("JNdelT",'Plantillas Meta'!H15)),"Sí","No") | D15: =LEN('Plantillas Meta'!H15)-LEN(SUBSTITUTE('Plantillas Meta'!H15,"?","")) | E15: 2 | F15: =IF(ISNUMBER(SEARCH("usted",'Plantillas Meta'!H15)),"Revisar","Sí") | G15: Sí | H15: =IF(LEFT(TRIM('Plantillas Meta'!H15),2)="{{","No","Sí") | I15: =IF(RIGHT(TRIM('Plantillas Meta'!H15),2)="}}","No","Sí") | J15: =IF(ISNUMBER(SEARCH("{{1}}",'Plantillas Meta'!H15)),"Sí","No") | K15: =IF(ISNUMBER(SEARCH("correo",'Plantillas Meta'!H15)),"Revisar","Sí") | L15: =IF(AND(B15<=1024,C15="Sí",D15<=1,E15<=3,F15="Sí",G15="Sí",H15="Sí",I15="Sí",K15="Sí"),"Cumple","Revisar")
A16: ='Plantillas Meta'!B16 | B16: =LEN('Plantillas Meta'!H16) | C16: =IF(ISNUMBER(SEARCH("JNdelT",'Plantillas Meta'!H16)),"Sí","No") | D16: =LEN('Plantillas Meta'!H16)-LEN(SUBSTITUTE('Plantillas Meta'!H16,"?","")) | E16: 2 | F16: =IF(ISNUMBER(SEARCH("usted",'Plantillas Meta'!H16)),"Revisar","Sí") | G16: Sí | H16: =IF(LEFT(TRIM('Plantillas Meta'!H16),2)="{{","No","Sí") | I16: =IF(RIGHT(TRIM('Plantillas Meta'!H16),2)="}}","No","Sí") | J16: =IF(ISNUMBER(SEARCH("{{1}}",'Plantillas Meta'!H16)),"Sí","No") | K16: =IF(ISNUMBER(SEARCH("correo",'Plantillas Meta'!H16)),"Revisar","Sí") | L16: =IF(AND(B16<=1024,C16="Sí",D16<=1,E16<=3,F16="Sí",G16="Sí",H16="Sí",I16="Sí",K16="Sí"),"Cumple","Revisar")
... A18: ='Plantillas Meta'!B18 | B18: =LEN('Plantillas Meta'!H18) | C18: =IF(ISNUMBER(SEARCH("JNdelT",'Plantillas Meta'!H18)),"Sí","No") | D18: =LEN('Plantillas Meta'!H18)-LEN(SUBSTITUTE('Plantillas Meta'!H18,"?","")) | E18: 2 | F18: =IF(ISNUMBER(SEARCH("usted",'Plantillas Meta'!H18)),"Revisar","Sí") | G18: Sí | H18: =IF(LEFT(TRIM('Plantillas Meta'!H18),2)="{{","No","Sí") | I18: =IF(RIGHT(TRIM('Plantillas Meta'!H18),2)="}}","No","Sí") | J18: =IF(ISNUMBER(SEARCH("{{1}}",'Plantillas Meta'!H18)),"Sí","No") | K18: =IF(ISNUMBER(SEARCH("correo",'Plantillas Meta'!H18)),"Revisar","Sí") | L18: =IF(AND(B18<=1024,C18="Sí",D18<=1,E18<=3,F18="Sí",G18="Sí",H18="Sí",I18="Sí",K18="Sí"),"Cumple","Revisar")
A20: Plantillas que cumplen | B20: =COUNTIF(L5:L18,"Cumple")&" de "&COUNTA(A5:A18)

Sheet Mensajes del agente
A1: Mensajes que el agente envía dentro de la conversación (no requieren aprobación de Meta)
A2: Desde el 26 oct estos textos son guías: el agente transmite su sentido con sus propias palabras y conserva exactos los datos (horarios, fechas, comisión, enlaces). Solo las plantillas de Meta se envían literales. El texto vigente de cada mensaje está en config/tenants/javier-nunez/plantillas.json.
A4: Clave | B4: Rol | C4: Texto actual | D4: Frases | E4: Preguntas | F4: Hallazgo | G4: Texto propuesto | H4: Aplicar (Sí/No)
A5: calificado | B5: lucia | C5: Gracias, cumples con los criterios para continuar. El siguiente paso es agendar una conversación con uno de nuestros asesores. ¿Cuál de estos horarios prefieres? {{horarios_disponibles}} | D5: 4 | E5: =LEN(C5)-LEN(SUBSTITUTE(C5,"?","")) | F5: 3 frases (Dapta: máximo 2). | G5: Perfecto, ya tenemos lo necesario para avanzar. ¿Cuál de estos horarios prefieres para hablar con un asesor? {{horarios_disponibles}}
A6: calificado | B6: sonia | C6: Gracias, ya contamos con la información necesaria y cumples con los criterios para continuar. Ahora puedes agendar una conversación con uno de nuestros asesores. ¿Cuál de estos horarios prefieres? {{horarios_disponibles}} | D6: 4 | E6: =LEN(C6)-LEN(SUBSTITUTE(C6,"?","")) | F6: 3 frases (Dapta: máximo 2). | G6: Perfecto, ya tenemos lo necesario para avanzar. ¿Cuál de estos horarios prefieres para hablar con un asesor? {{horarios_disponibles}}
A7: comentario_instagram | B7: común | C7: ¡Hola! Gracias por escribirnos. Envíanos un mensaje directo con la palabra INFO para poder ayudarte. | D7: 3 | E7: =LEN(C7)-LEN(SUBSTITUTE(C7,"?","")) | F7: Cumple. | H7: —
A8: confirmacion | B8: común | C8: Tu cita quedó confirmada para el {{fecha}} a las {{hora}}, zona horaria {{zona_horaria}}, mediante {{modalidad}}. El asesor asignado continuará contigo en ese momento. | D8: 2 | E8: =LEN(C8)-LEN(SUBSTITUTE(C8,"?","")) | F8: "zona horaria Colombia" se lee forzado. | G8: Listo, tu cita quedó confirmada para el {{fecha}} a las {{hora}}, hora de {{zona_horaria}}, por {{modalidad}}. Un asesor de JNdelT Real Estate te atenderá en ese momento.
A9: direccion_ambigua | B9: lucia | C9: No pude identificar la dirección con suficiente precisión. ¿Podrías confirmar la ciudad, el barrio y la dirección completa o compartir un punto de referencia? | D9: 2 | E9: =LEN(C9)-LEN(SUBSTITUTE(C9,"?","")) | F9: Pide cuatro datos en una sola pregunta (Dapta: una pregunta por turno). | G9: No logré ubicar la dirección con precisión. ¿Me confirmas la dirección completa con el barrio, o un punto de referencia cercano?
A10: enlace_agenda | B10: común | C10: Puedes escoger el horario que mejor te convenga aquí: {{enlace_agenda}}. La cita quedará confirmada cuando completes la reserva. | D10: 2 | E10: =LEN(C10)-LEN(SUBSTITUTE(C10,"?","")) | F10: Sin uso: no hay enlace de agenda configurado. | H10: —
A11: falla_agenda | B11: común | C11: No fue posible confirmar la cita en este momento. Tu información quedó registrada, pero el horario aún no está reservado. | D11: 2 | E11: =LEN(C11)-LEN(SUBSTITUTE(C11,"?","")) | F11: Cumple. | H11: —
A12: horario_agotado | B12: común | C12: Ese horario ya no se encuentra disponible. Puedo ofrecerte estas alternativas: {{horarios_alternativos}}. | D12: 2 | E12: =LEN(C12)-LEN(SUBSTITUTE(C12,"?","")) | F12: Cumple. | H12: —
A13: inicio | B13: lucia | C13: Hola, soy Lucía, la asistente virtual de JNdelT Real Estate. Te haré unas preguntas breves para conocer la propiedad que deseas vender o arrendar y determinar el siguiente paso. ¿Cuál es tu nombre? | D13: 3 | E13: =LEN(C13)-LEN(SUBSTITUTE(C13,"?","")) | F13: 3 frases y pregunta el nombre aunque el perfil ya lo tenga (Javier/Dapta: usar el primer nombre si es válido). El agente ya lo adapta, pero la plantilla debe reflejarlo. | G13: Hola, soy Lucía, la asistente virtual de JNdelT Real Estate. Te haré unas preguntas breves sobre la propiedad que quieres vender o arrendar.
A14: inicio | B14: sonia | C14: Hola, soy Sonia, la asistente virtual de JNdelT Real Estate. Te haré unas preguntas breves para entender qué propiedad buscas comprar o arrendar. ¿Cuál es tu nombre? | D14: 3 | E14: =LEN(C14)-LEN(SUBSTITUTE(C14,"?","")) | F14: Igual que la de Lucía. | G14: Hola, soy Sonia, la asistente virtual de JNdelT Real Estate. Te haré unas preguntas breves sobre la propiedad que buscas comprar o arrendar.
A15: no_calificado | B15: común | C15: Gracias por compartir la información. En este momento tu caso no cumple las condiciones necesarias para continuar con el proceso. | D15: 2 | E15: =LEN(C15)-LEN(SUBSTITUTE(C15,"?","")) | F15: Sin uso mientras nutricion.incluir_no_calificados = true. | H15: —
A16: no_calificado_nutricion | B16: común | C16: Gracias por compartir la información. Por ahora no podemos avanzar con una cita, pero quedas registrado y te compartiremos información útil para tu proceso. Cuando quieras retomar, escríbenos por aquí. | D16: 3 | E16: =LEN(C16)-LEN(SUBSTITUTE(C16,"?","")) | F16: 3 frases (Dapta: máximo 2). | G16: Gracias por la información; por ahora no podemos avanzar con una cita, pero quedas registrado. Te compartiremos información útil y puedes escribirnos cuando quieras retomar.
A17: pendiente_agenda | B17: común | C17: Ya completamos la calificación. Para continuar, todavía debes seleccionar una fecha y hora para conversar con un asesor: {{enlace_agenda}}. | D17: 2 | E17: =LEN(C17)-LEN(SUBSTITUTE(C17,"?","")) | F17: Necesita aprobación de Meta (se envía fuera de la conversación) y depende de un enlace de agenda que no existe. Se reemplaza por jndelt_recordatorio_agendar. | H17: —
A18: prioridad_baja | B18: común | C18: Gracias, ya tenemos la información que necesitamos. Como aún no tienes prisa, por ahora no agendaremos una cita: quedas registrado y te compartiremos información útil para tu proceso. Cuando quieras avanzar, escríbenos por aquí. | D18: 3 | E18: =LEN(C18)-LEN(SUBSTITUTE(C18,"?","")) | F18: 3 frases (Dapta: máximo 2). | G18: Gracias, ya tenemos lo necesario; como aún no tienes prisa, por ahora no agendaremos una cita. Quedas registrado y puedes escribirnos por aquí cuando quieras avanzar.
A19: seleccion_intencion | B19: común | C19: Hola, soy el asistente virtual de JNdelT Real Estate. Para orientarte correctamente, cuéntame: ¿quieres vender o arrendar una propiedad tuya, o estás buscando una propiedad para comprar o arrendar? | D19: 2 | E19: =LEN(C19)-LEN(SUBSTITUTE(C19,"?","")) | F19: Cumple. | H19: —
